{"doc":"","fields":[],"enumConstants":[],"methods":[{"name":"stationsInfo","paramTypes":["org.dromara.omind.userplat.api.domain.request.QueryStationsInfoData","org.dromara.omind.userplat.api.domain.entity.OmindOperatorEntity"],"doc":" 查询运营商的充电站的信息\n 接口名称：query_stations_info\n @return\n"},{"name":"stationStatus","paramTypes":["org.dromara.omind.userplat.api.domain.request.QueryStationStatusData","org.dromara.omind.userplat.api.domain.entity.OmindOperatorEntity"],"doc":" 设备接口状态查询\n 接口名称：query_station_status\n @return\n"},{"name":"equipBusinessPolicyQuery","paramTypes":["org.dromara.omind.userplat.api.domain.request.QueryEquipBusinessPolicyData","org.dromara.omind.userplat.api.domain.entity.OmindOperatorEntity"],"doc":" 查询业务策略信息结果\n 接口名称：query_equip_business_policy\n @return\n"},{"name":"equipAuth","paramTypes":["org.dromara.omind.userplat.api.domain.request.QueryEquipAuthData"],"doc":" 请求设备认证\n 接口名称：query_equip_auth\n @return\n"},{"name":"startCharge","paramTypes":["org.dromara.omind.userplat.api.domain.request.QueryStartChargeData"],"doc":" 请求启动充电\n 接口名称：query_start_charge\n @return\n"},{"name":"stopCharge","paramTypes":["org.dromara.omind.userplat.api.domain.request.QueryStopChargeData"],"doc":" 请求停止充电\n 接口名称：query_stop_charge\n @return\n"},{"name":"equipChargeStatus","paramTypes":["org.dromara.omind.userplat.api.domain.request.QueryEquipChargeStatusData","org.dromara.omind.userplat.api.domain.entity.OmindOperatorEntity"],"doc":" 查询充电状态\n 接口名称：query_equip_charge_status\n @return\n"}],"constructors":[]}